ccpp_test/__init__.py
ccpp_test/main.py
ccpp_test-0.1.0.dist-info/entry_points.txt
ccpp_test-0.1.0.dist-info/LICENSE
ccpp_test-0.1.0.dist-info/WHEEL
ccpp_test-0.1.0.dist-info/METADATA
ccpp_test-0.1.0.dist-info/RECORD
