Metadata-Version: 2.1
Name: ccpp-test
Version: 0.1.0
Summary: 
Home-page: https://github.com/guaifish/ccpp-test
License: MIT
Author: guaifish
Author-email: guaifish@hotmail.com
Requires-Python: >=3.6,<4.0
Classifier: License :: OSI Approved :: MIT License
Classifier: Programming Language :: Python :: 3
Classifier: Programming Language :: Python :: 3.6
Classifier: Programming Language :: Python :: 3.7
Requires-Dist: fire (>=0.3.1,<0.4.0)
Project-URL: Repository, https://github.com/guaifish/ccpp-test
